mathans/__init__.py
mathans/algorithms.py
mathans/questions.py
mathans/tickets.py
mathans-0.1.6.dist-info/licenses/LICENSE
mathans-0.1.6.dist-info/METADATA
mathans-0.1.6.dist-info/WHEEL
mathans-0.1.6.dist-info/top_level.txt
mathans-0.1.6.dist-info/RECORD
